sista/__init__.py
sista/__init__.pyi
sista/_sista.cpython-314-x86_64-linux-musl.so
sista.libs/libSista-360f1f1b.so.3.0.0-alpha.21
sista.libs/libSista_api-2c55333d.so.3.0.0-alpha.21
sista.libs/libgcc_s-0cd532bd.so.1
sista.libs/libstdc++-5d72f927.so.6.0.33
sista-3.0.0a21.dist-info/METADATA
sista-3.0.0a21.dist-info/WHEEL
sista-3.0.0a21.dist-info/top_level.txt
sista-3.0.0a21.dist-info/RECORD
sista-3.0.0a21.dist-info/licenses/LICENSE.md
sista-3.0.0a21.dist-info/sboms/auditwheel.cdx.json
