Metadata-Version: 2.4
Name: sista
Version: 3.0.0a21
Summary: Sista is a memory-safe and OS-agnostic library for making terminal videogames and animations
Author-email: FLAK-ZOSO <mattia.marchese.2006@gmail.com>
License-Expression: GPL-3.0-only
Project-URL: Homepage, https://github.com/FLAK-ZOSO/Sista
Project-URL: Repository, https://github.com/FLAK-ZOSO/Sista
Project-URL: Documentation, https://flak-zoso.github.io/Sista/
Project-URL: Changelog, https://github.com/FLAK-ZOSO/Sista/blob/main/changelog.md
Project-URL: ReleaseNotes, https://github.com/FLAK-ZOSO/Sista/blob/main/ReleaseNotes.md
Keywords: ansi,graphics,terminal,videogames,animations
Classifier: Development Status :: 3 - Alpha
Classifier: Intended Audience :: Developers
Classifier: Natural Language :: English
Classifier: Operating System :: OS Independent
Classifier: Operating System :: Unix
Classifier: Operating System :: MacOS
Classifier: Programming Language :: Python :: 3
Classifier: Programming Language :: Python :: 3.10
Classifier: Programming Language :: Python :: 3.11
Classifier: Programming Language :: Python :: 3.12
Classifier: Programming Language :: Python :: 3.13
Classifier: Programming Language :: Python :: 3.14
Classifier: Programming Language :: Python :: Implementation :: CPython
Classifier: Topic :: Games/Entertainment
Classifier: Topic :: Games/Entertainment :: Simulation
Requires-Python: >=3.10
License-File: LICENSE.md
Dynamic: license-file
